yobr
