Metadata-Version: 1.2
Name: yobr
Version: 0.6.0
Summary: Graphical Buildroot build monitor
Home-page: https://github.com/eepp/yobr
Author: Philippe Proulx
Author-email: eeppeliteloop@gmail.com
License: UNKNOWN
Keywords: buildroot build monitor build-monitor gui
Platform: UNKNOWN
Classifier: Environment :: X11 Applications :: Qt
Classifier: Intended Audience :: Developers
Classifier: License :: OSI Approved :: MIT License
Classifier: Natural Language :: English
Classifier: Programming Language :: Python :: 3 :: Only
Classifier: Topic :: Software Development :: User Interfaces
Requires-Python: >=3.4
